printstream/__init__.py
printstream/activate.py
printstream/config.py
printstream-0.1.3.dist-info/LICENSE
printstream-0.1.3.dist-info/METADATA
printstream-0.1.3.dist-info/WHEEL
printstream-0.1.3.dist-info/top_level.txt
printstream-0.1.3.dist-info/RECORD
