Metadata-Version: 2.1
Name: printstream
Version: 0.1.3
Summary: A library for enhanced print debugging.
Home-page: https://github.com/arnav-ag/printstream
Author: Arnav
Author-email: arnavaggarwalwork@gmail.com
Classifier: Programming Language :: Python :: 3
Classifier: License :: OSI Approved :: MIT License
License-File: LICENSE
Requires-Dist: termcolor
